kitdex/__init__.py
kitdex/__main__.py
kitdex/database.py
kitdex/utilities.py
kitdex/static/jquery-3.5.1.js
kitdex/static/jquery.dataTables.min.css
kitdex/static/jquery.dataTables.min.js
kitdex/static/natural.js
kitdex/templates/index.jinja
kitdex/templates/rename_location.jinja
kitdex/templates/update_locations.jinja
kitdex/templates/update_thing.jinja
kitdex-0.0.2.dist-info/LICENSE
kitdex-0.0.2.dist-info/METADATA
kitdex-0.0.2.dist-info/WHEEL
kitdex-0.0.2.dist-info/entry_points.txt
kitdex-0.0.2.dist-info/top_level.txt
kitdex-0.0.2.dist-info/RECORD
