Metadata-Version: 2.1
Name: kitdex
Version: 0.0.2
Summary: An index for where to find your kit.
Home-page: UNKNOWN
Author: Julian Stirling
Author-email: julian@julianstirling.co.uk
License: GPLv3
Project-URL: Bug Tracker, https://gitlab.com/julianstirling/kitdex/issues
Project-URL: Source Code, https://gitlab.com/julianstirling/kitdex
Keywords: Organisation,Hardware
Platform: UNKNOWN
Classifier: Development Status :: 5 - Production/Stable
Classifier: License :: OSI Approved :: GNU General Public License v3 (GPLv3)
Classifier: Programming Language :: Python :: 3.6
Requires-Python: >=3.6
Requires-Dist: argparse
Requires-Dist: flask
Requires-Dist: jinja2
Requires-Dist: marshmallow (<3.12,>=03.8)
Requires-Dist: pywebview[qt]
Requires-Dist: pyyaml (>=5.1)
Requires-Dist: requests
